drgpy/__init__.py
drgpy/_appndxrdr.py
drgpy/_mdcs0007.py
drgpy/_mdcs0811.py
drgpy/_mdcs1221.py
drgpy/_mdcs2225.py
drgpy/_mdcsrdr.py
drgpy/_msdrg.py
drgpy/msdrg.py
drgpy/msdrg_allvers.py
drgpy/data/__init__.py
drgpy/data/pbl-049_hcpcs-drg_defman.txt
drgpy/data/v36/appendix_A.txt
drgpy/data/v36/appendix_B.txt
drgpy/data/v36/appendix_C.txt
drgpy/data/v36/appendix_D_E.txt
drgpy/data/v36/appendix_F_J.txt
drgpy/data/v36/mdcs_00_07.txt
drgpy/data/v36/mdcs_08_11.txt
drgpy/data/v36/mdcs_12_21.txt
drgpy/data/v36/mdcs_22_25.txt
drgpy/data/v37/appendix_A.txt
drgpy/data/v37/appendix_B.txt
drgpy/data/v37/appendix_C.txt
drgpy/data/v37/appendix_D_E.txt
drgpy/data/v37/appendix_F_J.txt
drgpy/data/v37/mdcs_00_07.txt
drgpy/data/v37/mdcs_08_11.txt
drgpy/data/v37/mdcs_12_21.txt
drgpy/data/v37/mdcs_22_25.txt
drgpy/data/v38/appendix_A.txt
drgpy/data/v38/appendix_B.txt
drgpy/data/v38/appendix_C.txt
drgpy/data/v38/appendix_D_E.txt
drgpy/data/v38/appendix_F_J.txt
drgpy/data/v38/mdcs_00_07.txt
drgpy/data/v38/mdcs_08_11.txt
drgpy/data/v38/mdcs_12_21.txt
drgpy/data/v38/mdcs_22_25.txt
drgpy/data/v39/appendix_A.txt
drgpy/data/v39/appendix_B.txt
drgpy/data/v39/appendix_C.txt
drgpy/data/v39/appendix_D_E.txt
drgpy/data/v39/appendix_F_J.txt
drgpy/data/v39/mdcs_00_07.txt
drgpy/data/v39/mdcs_08_11.txt
drgpy/data/v39/mdcs_12_21.txt
drgpy/data/v39/mdcs_22_25.txt
drgpy/data/v40/appendix_A.txt
drgpy/data/v40/appendix_B.txt
drgpy/data/v40/appendix_C.txt
drgpy/data/v40/appendix_D_E.txt
drgpy/data/v40/appendix_F_J.txt
drgpy/data/v40/mdcs_00_07.txt
drgpy/data/v40/mdcs_08_11.txt
drgpy/data/v40/mdcs_12_21.txt
drgpy/data/v40/mdcs_22_25.txt
tests/__init__.py
tests/test_debug.py
tests/test_mdc00.py
tests/test_mdc01.py
tests/test_mdc02.py
tests/test_mdc03.py
tests/test_mdc04.py
tests/test_mdc05.py
tests/test_mdc06.py
tests/test_mdc07.py
tests/test_mdc08.py
tests/test_mdc09.py
tests/test_mdc10.py
tests/test_mdc11.py
tests/test_mdc12.py
tests/test_mdc13.py
tests/test_mdc14.py
tests/test_mdc15.py
tests/test_mdc16.py
drgpy-0.0.6.dist-info/LICENSE.txt
drgpy-0.0.6.dist-info/METADATA
drgpy-0.0.6.dist-info/WHEEL
drgpy-0.0.6.dist-info/top_level.txt
drgpy-0.0.6.dist-info/RECORD
