Metadata-Version: 2.1
Name: drgpy
Version: 0.0.6
Summary: drgpy is a Python library for assigning a combination of diagnosis and procedure codes to Diagnosis Related Groups (MS-DRG) that is used in Medicare inpatient reimbursement today.
Home-page: https://github.com/yubin-park/drgpy
Author: Yubin Park
Author-email: yubin.park@gmail.com
License: Apache 2.0
Classifier: Programming Language :: Python :: 3
Classifier: License :: OSI Approved :: Apache Software License
Classifier: Operating System :: OS Independent
License-File: LICENSE.txt
